[
  {
    "name": "ლადო",
    "phone": "555 25-89-21",
    "address": {
      "city": "თბილისი",
      "street": "დიდუბის ქ. # 31"
    }
  },
  {
    "name": "ნინო",
    "phone": "555 21-00-08",
    "address": {
      "city": "თბილისი",
      "street": "ლადო გუდიაშვილის ქ. # 19"
    }
  },
  {
    "name": "არჩილ",
    "phone": "599 22-33-44",
    "address": {
      "city": "თელავი",
      "street": "კახეთის ქ. # 8"
    }
  },
  {
    "name": "თათია",
    "phone": "597 16-98-01",
    "address": {
      "city": "ფოთი",
      "street": "ზვიად გამსახურდიას ქ. # 28"
    }
  }
]